autogroceries/__init__.py
autogroceries/cli.py
autogroceries/delay.py
autogroceries/exceptions.py
autogroceries/logging.py
autogroceries/shopper/__init__.py
autogroceries/shopper/base.py
autogroceries/shopper/sainsburys.py
autogroceries/shopper/waitrose.py
autogroceries-2.2.3.dist-info/METADATA
autogroceries-2.2.3.dist-info/WHEEL
autogroceries-2.2.3.dist-info/entry_points.txt
autogroceries-2.2.3.dist-info/licenses/LICENSE
autogroceries-2.2.3.dist-info/RECORD
