Metadata-Version: 2.4
Name: autogroceries
Version: 2.2.3
Summary: Automate your grocery shop.
Author: David Zhang
License: MIT License
License-File: LICENSE
Requires-Python: >=3.13
Requires-Dist: click==8.2.1
Requires-Dist: playwright==1.54.0
Requires-Dist: python-dotenv==1.1.1
Provides-Extra: build
Requires-Dist: build==1.3.0; extra == 'build'
Provides-Extra: dev
Requires-Dist: pre-commit==4.3.0; extra == 'dev'
Requires-Dist: pytest-cov==6.0.0; extra == 'dev'
Requires-Dist: pytest==8.4.1; extra == 'dev'
Provides-Extra: docs
Requires-Dist: mkdocs-material==9.6.18; extra == 'docs'
Requires-Dist: mkdocs==1.6.1; extra == 'docs'
Requires-Dist: mkdocstrings[python]==0.30.0; extra == 'docs'
